sense_requests/__init__.py
sense_requests/cli/__init__.py
sense_requests/config/__init__.py
sense_requests/constants/__init__.py
sense_requests/core/__init__.py
sense_requests/core/client.py
sense_requests/core/config.py
sense_requests/core/log.py
sense_requests/core/request.py
sense_requests/db/__init__.py
sense_requests/pipelines/__init__.py
sense_requests/utils/__init__.py
sense_requests/utils/scrapy.py
sense_requests_sdk-1.0.2.dist-info/METADATA
sense_requests_sdk-1.0.2.dist-info/RECORD
sense_requests_sdk-1.0.2.dist-info/WHEEL
sense_requests_sdk-1.0.2.dist-info/entry_points.txt
sense_requests_sdk-1.0.2.dist-info/top_level.txt
