Metadata-Version: 2.1
Name: sense-requests-sdk
Version: 1.0.2
Summary: Python SDK for Sense-Requests
Home-page: UNKNOWN
Author: kafka0102
Author-email: yujianjia@sensedeal.ai
License: BSD License
Platform: UNKNOWN
Classifier: Programming Language :: Python :: 3
Classifier: License :: OSI Approved :: BSD License
Classifier: Operating System :: OS Independent
Requires-Dist: Click
Requires-Dist: requests
Requires-Dist: prettytable
Requires-Dist: scrapy
Requires-Dist: pymongo
